rspylog/__init__.py
rspylog/api_handler.py
rspylog/config.py
rspylog/footprint.py
rspylog/formatter.py
rspylog/handlers.py
rspylog/initializer.py
rspylog-0.1.3.dist-info/METADATA
rspylog-0.1.3.dist-info/WHEEL
rspylog-0.1.3.dist-info/RECORD
