Metadata-Version: 2.3
Name: rspylog
Version: 0.1.3
Summary: A light python package for advanced python log system.
License: MIT
Author: Reza Shirazi
Author-email: itreza7@gmail.com
Requires-Python: >=3.11,<4.0
Classifier: License :: OSI Approved :: MIT License
Classifier: Programming Language :: Python :: 3
Classifier: Programming Language :: Python :: 3.11
Classifier: Programming Language :: Python :: 3.12
Classifier: Programming Language :: Python :: 3.13
Requires-Dist: requests (>=2.32.3,<3.0.0)
Project-URL: Repository, https://github.com/itreza7/rspylog
